CMakeLists.txt
MANIFEST.in
README.md
setup.py
CarnaPy.egg-info/PKG-INFO
CarnaPy.egg-info/SOURCES.txt
CarnaPy.egg-info/dependency_links.txt
CarnaPy.egg-info/requires.txt
CarnaPy.egg-info/top_level.txt
misc/VERSIONS.yaml
misc/__init__.py.in
misc/build-conda-recipe.sh
misc/compiler_specific.cmake
misc/distribute_to_pypi.sh
misc/install_local.sh
misc/py.py
misc/CMake-Modules/FindEigen3.cmake
misc/conda-recipe/bootstrap.sh
misc/conda-recipe/build_recipe.sh
misc/conda-recipe/carnapy/build.sh
misc/conda-recipe/carnapy/meta.yaml
misc/conda-recipe/carnapy.in/.build.sh.swp
misc/conda-recipe/carnapy.in/build.sh
misc/conda-recipe/carnapy.in/meta.yaml
src/egl/Context.cpp
src/include/Carna/egl/Context.h
src/include/Carna/py/Surface.h
src/include/Carna/py/py.h
src/py/Surface.cpp
src/py/base.cpp
src/py/egl.cpp
src/py/helpers.cpp
src/py/presets.cpp
test/CMakeLists.txt
test/test_base.py
test/test_helpers.py
test/test_presets.py
test/test_py.py
test/test_py_demo1.py
test/test_py_demo2.py
test/test_py_demo3.py
test/test_py_demo4.py
test/test_py_demo5.py
test/test_tools.py
test/renderings/helpers.FrameRendererHelper.uint16.png
test/renderings/helpers.FrameRendererHelper.uint8.png
test/renderings/presets.CuttingPlanesStage.png
test/renderings/presets.DVRStage.png
test/renderings/presets.MIPStage.png
test/renderings/presets.MaskRenderingStage.png
test/renderings/presets.MaskRenderingStage.render_borders.png
test/renderings/presets.OpaqueRenderingStage.png
test/renderings/py.demo1.png
test/renderings/py.demo2.png
test/renderings/py.demo3.borders-in-background.png
test/renderings/py.demo3.borders-on-top.png
test/renderings/py.demo3.regions-on-top.png
test/renderings/py.demo3.regions.png
test/renderings/py.demo4.normalized.ms-front.png
test/renderings/py.demo4.normalized.ms-left.png
test/renderings/py.demo4.normalized.ms-top.png
test/renderings/py.demo4.normalized.ss-front.png
test/renderings/py.demo4.normalized.ss-left.png
test/renderings/py.demo4.normalized.ss-top.png
test/renderings/py.demo5.png