Metadata-Version: 2.1
Name: CarnaPy
Version: 0.1.5
Summary: General-purpose real-time 3D visualization
Home-page: https://github.com/kostrykin/CarnaPy
Author: Leonid Kostrykin
Author-email: leonid.kostrykin@bioquant.uni-heidelberg.de
License: BSD
Platform: UNKNOWN
Classifier: Development Status :: 3 - Alpha
Classifier: Environment :: GPU
Classifier: License :: OSI Approved :: BSD License
Classifier: Operating System :: POSIX :: Linux
Classifier: Programming Language :: C++
Classifier: Programming Language :: Python
Classifier: Topic :: Education
Classifier: Topic :: Multimedia :: Graphics :: 3D Rendering
Classifier: Topic :: Scientific/Engineering :: Visualization
Classifier: Topic :: Software Development :: User Interfaces
